aspect_library_v1
