Metadata-Version: 2.1
Name: aspect-library-v1
Version: 0.1.3
Summary: A Python library for aspect-based sentiment analysis with translation capabilities
Home-page: https://github.com/yourusername/my_aspect_library
Author: Your Name
Author-email: your.email@example.com
Classifier: Programming Language :: Python :: 3
Classifier: License :: OSI Approved :: MIT License
Classifier: Operating System :: OS Independent
Requires-Python: >=3.6
